nlp_model_gen_plugins/__init__.py
nlp_model_gen_plugins/base.py
nlp_model_gen_plugins/constants.py
nlp_model_gen_plugins/__pycache__/__init__.cpython-36.pyc
nlp_model_gen_plugins/__pycache__/constants.cpython-36.pyc
nlp_model_gen_plugins/plugins/whatsappPlugin/WhatsappExtract.py
nlp_model_gen_plugins/plugins/whatsappPlugin/WhatsappMessage.py
nlp_model_gen_plugins/plugins/whatsappPlugin/whatsappPlugin.py
nlp_model_gen_plugins/plugins/whatsappPlugin/__pycache__/WhatsappExtract.cpython-36.pyc
nlp_model_gen_plugins/plugins/whatsappPlugin/__pycache__/WhatsappMessage.cpython-36.pyc
nlp_model_gen_plugins/plugins/whatsappPlugin/__pycache__/whatsappPlugin.cpython-36.pyc
nlp_model_gen_plugins/utils/collectionsUtils.py
nlp_model_gen_plugins/utils/__pycache__/collectionsUtils.cpython-36.pyc
nlp_model_gen_plugins-0.1.2.dist-info/DESCRIPTION.rst
nlp_model_gen_plugins-0.1.2.dist-info/METADATA
nlp_model_gen_plugins-0.1.2.dist-info/RECORD
nlp_model_gen_plugins-0.1.2.dist-info/WHEEL
nlp_model_gen_plugins-0.1.2.dist-info/metadata.json
nlp_model_gen_plugins-0.1.2.dist-info/top_level.txt
