Metadata-Version: 2.0
Name: nlp-model-gen-plugins
Version: 0.1.2
Summary: NLP admin plugins
Home-page: https://github.com/galias11/nlp_model_gen_plugins
Author: Gerardo Alias
Author-email: alias_gerardo@yahoo.com.ar
License: UNKNOWN
Platform: UNKNOWN
Classifier: Programming Language :: Python :: 3
Classifier: License :: OSI Approved :: MIT License
Classifier: Operating System :: OS Independent
